{
	"Objects": [
		{
			"Name":"QuercusPetrae_30m",
			"Definition":[
				{
					"Name":"QuercusPetrae_30m_TheGroveBranches",
					"File":"QuercusPetrae_30m_TheGroveBranches.serialized",
					"Material": {
						"Type":"Textured",
						"ColorMap":"QuercusPetrae.jpg",
						"UVScale": 1.0
					},
					"Instances": [
						{"Rotate": [-1.5708,0,0], "Translate": [0,0,0], "Scale": [1,1,1]}
					]
				}
,				{
					"Name":"QuercusPetrae_30m_LeafTop",
					"File":"QuercusPetrae_30m_LeafTop.serialized",
					"Material": {
						"Type":"Textured",
						"ColorMap":"QuercusPetrea-Top-albedo.png",
						"OpacityMap":"QuercusPetrea-Top-alpha.png",
						"UVScale": 1.0
					},
					"Instances": [
						{"Rotate": [-1.5708,0,0], "Translate": [0,0,0], "Scale": [1,1,1]}
					]
				}
,				{
					"Name":"QuercusPetrae_30m_LeafFront",
					"File":"QuercusPetrae_30m_LeafFront.serialized",
					"Material": {
						"Type":"Textured",
						"ColorMap":"QuercusPetrea-Front-albedo.png",
						"OpacityMap":"QuercusPetrea-Front-alpha.png",
						"UVScale": 1.0
					},
					"Instances": [
						{"Rotate": [-1.5708,0,0], "Translate": [0,0,0], "Scale": [1,1,1]}
					]
				}
			]
		}
	]
}